LingjixianX3/README.md
LingjixianX3/__init__.py
LingjixianX3/__main__.py
LingjixianX3/file.epub
LingjixianX3/index.html
LingjixianX3/css/__init__.py
LingjixianX3/css/annotations.css
LingjixianX3/css/main.css
LingjixianX3/css/normalize.css
LingjixianX3/css/popup.css
LingjixianX3/font/__init__.py
LingjixianX3/font/fontello.eot
LingjixianX3/font/fontello.svg
LingjixianX3/font/fontello.ttf
LingjixianX3/font/fontello.woff
LingjixianX3/img/__init__.py
LingjixianX3/img/annotator-glyph-sprite.png
LingjixianX3/img/annotator-icon-sprite.png
LingjixianX3/img/apple-touch-icon.png
LingjixianX3/img/cancelfullscreen.png
LingjixianX3/img/close.png
LingjixianX3/img/fullscreen.png
LingjixianX3/img/loader.gif
LingjixianX3/img/menu-icon.png
LingjixianX3/img/save.png
LingjixianX3/img/saved.png
LingjixianX3/img/settings-s.png
LingjixianX3/img/settings.png
LingjixianX3/img/star.png
LingjixianX3/js/__init__.py
LingjixianX3/js/epub.js
LingjixianX3/js/epub.min.js
LingjixianX3/js/epub.min.map
LingjixianX3/js/hooks.min.js
LingjixianX3/js/hooks.min.map
LingjixianX3/js/reader.js
LingjixianX3/js/reader.js.map
LingjixianX3/js/reader.min.js
LingjixianX3/js/reader.min.map
LingjixianX3/js/hooks/__init__.py
LingjixianX3/js/hooks/extensions/__init__.py
LingjixianX3/js/hooks/extensions/highlight.js
LingjixianX3/js/libs/__init__.py
LingjixianX3/js/libs/jquery.min.js
LingjixianX3/js/libs/localforage.min.js
LingjixianX3/js/libs/screenfull.js
LingjixianX3/js/libs/screenfull.min.js
LingjixianX3/js/libs/zip.min.js
LingjixianX3/js/plugins/__init__.py
LingjixianX3/js/plugins/hypothesis.js
LingjixianX3/js/plugins/search.js
lingjixian_x3-2022.9.29.0.dist-info/METADATA
lingjixian_x3-2022.9.29.0.dist-info/WHEEL
lingjixian_x3-2022.9.29.0.dist-info/entry_points.txt
lingjixian_x3-2022.9.29.0.dist-info/top_level.txt
lingjixian_x3-2022.9.29.0.dist-info/RECORD
